{
  "format_version": "1.20.20",
  "minecraft:block": {
    "description": {
      "identifier": "rainbow:blue_700_lit",
      "menu_category": {
        "category": "construction",
        "group": "itemGroup.name.glazedTerracotta"
      },
      "traits": {}
    },
    "components": {
      "minecraft:unit_cube": {},
      "minecraft:map_color": "#1b2136",
      "minecraft:light_emission": 15,
      "minecraft:material_instances": {
        "*": {
          "texture": "rainbow_blue_700_lit",
          "render_method": "opaque"
        }
      }
    }
  }
}